[
  {
    "name": "Doing well?",
    "canonical": "enoughSleep && keepingUp",
    "answer": "enoughSleep && keepingUp",
    "correct": true,
    "timestamp": 1663797433978
  },
  {
    "name": "Energetic?",
    "canonical": "enoughSleep && !justWorkedOut",
    "answer": "enoughSleep && ! justWorkedOut",
    "correct": true,
    "timestamp": 1663797455250
  },
  {
    "name": "Dragging?",
    "canonical": "!enoughSleep && lotsOfWork",
    "answer": "! enoughSleep && lotsOfWork",
    "correct": true,
    "timestamp": 1663797482747
  }
]