[
  {
    "name": "Doing well?",
    "canonical": "enoughSleep && keepingUp",
    "answer": "enoughSleep && keepingUp",
    "correct": true,
    "timestamp": 1662588448210
  },
  {
    "name": "Energetic?",
    "canonical": "enoughSleep && !justWorkedOut",
    "answer": "enoughSleep && ! justWorkedOut",
    "correct": true,
    "timestamp": 1662588461803
  },
  {
    "name": "Dragging?",
    "canonical": "!enoughSleep && lotsOfWork",
    "answer": "! enoughSleep && lotsOfWork",
    "correct": true,
    "timestamp": 1662588479907
  },
  {
    "name": "Super beat?",
    "canonical": "!enoughSleep && !eatenEnough",
    "answer": "! enoughSleep && ! eatenEnough",
    "correct": true,
    "timestamp": 1662673614713
  },
  {
    "name": "Can go to prom?",
    "canonical": "isSenior || invitedBySenior",
    "answer": "isSenior || invitedBySenior",
    "correct": true,
    "timestamp": 1662673666113
  },
  {
    "name": "Having fun?",
    "canonical": "done || !fun",
    "answer": "done || ! fun",
    "correct": true,
    "timestamp": 1662673723275
  },
  {
    "name": "Not feeling it?",
    "canonical": "!fun || tired",
    "answer": "! fun && tired",
    "correct": false,
    "timestamp": 1662673733804
  },
  {
    "name": "Not feeling it?",
    "canonical": "!fun || tired",
    "answer": "! fun || tired",
    "correct": true,
    "timestamp": 1662673741476
  },
  {
    "name": "Time to sleep?",
    "canonical": "!sleepy || !dark",
    "answer": "! sleep || ! dark",
    "correct": false,
    "timestamp": 1662673752076
  },
  {
    "name": "Time to sleep?",
    "canonical": "!sleepy || !dark",
    "answer": "! sleep && ! dark",
    "correct": false,
    "timestamp": 1662673759428
  },
  {
    "name": "Time to sleep?",
    "canonical": "!sleepy || !dark",
    "answer": "! sleepy && ! dark",
    "correct": false,
    "timestamp": 1662673765172
  },
  {
    "name": "Time to sleep?",
    "canonical": "!sleepy || !dark",
    "answer": "! sleepy || ! dark",
    "correct": true,
    "timestamp": 1662673770676
  }
]